vaultlens/__init__.py
vaultlens/analyzer.py
vaultlens/auditor.py
vaultlens/feedback.py
vaultlens/main.py
vaultlens/reporter.py
vault_lens-0.1.3.dist-info/METADATA
vault_lens-0.1.3.dist-info/WHEEL
vault_lens-0.1.3.dist-info/entry_points.txt
vault_lens-0.1.3.dist-info/top_level.txt
vault_lens-0.1.3.dist-info/RECORD
