Metadata-Version: 2.4
Name: Vault_Lens
Version: 0.1.3
Summary: Vault_Lens lets you run private datasets locally and gives Ollama a lens to see in the vault. Raw data is never touched by the llm.
Author-email: Steven Polino <stpolino@gmail.com>
License: MIT
Project-URL: Homepage, https://github.com/CharSiu8/Vault_Lens
Project-URL: GithubPage, https://charsiu8.github.io/Vault_Lens/
Project-URL: Bug Tracker, https://github.com/yourusername/vaultlens/issues
Classifier: Programming Language :: Python :: 3
Classifier: License :: OSI Approved :: MIT License
Classifier: Operating System :: OS Independent
Requires-Python: >=3.7
